odoo/addons/account_tax_unece/README.rst
odoo/addons/account_tax_unece/__init__.py
odoo/addons/account_tax_unece/__manifest__.py
odoo/addons/account_tax_unece/data/unece_tax_categ.xml
odoo/addons/account_tax_unece/data/unece_tax_type.xml
odoo/addons/account_tax_unece/i18n/account_tax_unece.pot
odoo/addons/account_tax_unece/i18n/de.po
odoo/addons/account_tax_unece/i18n/es.po
odoo/addons/account_tax_unece/i18n/fr.po
odoo/addons/account_tax_unece/i18n/it.po
odoo/addons/account_tax_unece/models/__init__.py
odoo/addons/account_tax_unece/models/account_tax.py
odoo/addons/account_tax_unece/models/res_company.py
odoo/addons/account_tax_unece/models/unece_code_list.py
odoo/addons/account_tax_unece/readme/CONFIGURE.md
odoo/addons/account_tax_unece/readme/CONTRIBUTORS.md
odoo/addons/account_tax_unece/readme/DESCRIPTION.md
odoo/addons/account_tax_unece/static/description/icon.png
odoo/addons/account_tax_unece/static/description/index.html
odoo/addons/account_tax_unece/tests/__init__.py
odoo/addons/account_tax_unece/tests/test_tax_unece.py
odoo/addons/account_tax_unece/views/account_tax.xml
odoo/addons/account_tax_unece/views/unece_code_list.xml
odoo_addon_account_tax_unece-18.0.1.0.0.4.dist-info/METADATA
odoo_addon_account_tax_unece-18.0.1.0.0.4.dist-info/WHEEL
odoo_addon_account_tax_unece-18.0.1.0.0.4.dist-info/top_level.txt
odoo_addon_account_tax_unece-18.0.1.0.0.4.dist-info/RECORD
